<?xml version="1.1" encoding="UTF-8" standalone="no"?>
<databaseChangeLog xmlns="http://www.liquibase.org/xml/ns/dbchangelog" xmlns:ext="http://www.liquibase.org/xml/ns/dbchangelog-ext" xmlns:xsi="http://www.w3.org/2001/XMLSchema-instance" xsi:schemaLocation="http://www.liquibase.org/xml/ns/dbchangelog-ext http://www.liquibase.org/xml/ns/dbchangelog/dbchangelog-ext.xsd http://www.liquibase.org/xml/ns/dbchangelog http://www.liquibase.org/xml/ns/dbchangelog/dbchangelog-3.5.xsd">
    <changeSet author="akarnov (generated)" id="1492450531672-1">
        <insert tableName="Grup">
            <column name="idGroups" valueNumeric="10"/>
            <column name="Title" value="title"/>
        </insert>
        <insert tableName="Grup">
            <column name="idGroups" valueNumeric="11"/>
            <column name="Title" value="title1"/>
        </insert>
        <insert tableName="Grup">
            <column name="idGroups" valueNumeric="12"/>
            <column name="Title" value="title2"/>
        </insert>
        <insert tableName="Grup">
            <column name="idGroups" valueNumeric="13"/>
            <column name="Title" value="title3"/>
        </insert>
    </changeSet>
    <changeSet author="akarnov (generated)" id="1492450531672-2">
        <insert tableName="Room">
            <column name="idRooms" valueNumeric="14"/>
            <column name="Title" value="room1"/>
            <column name="MaxMembers" valueNumeric="10"/>
        </insert>
        <insert tableName="Room">
            <column name="idRooms" valueNumeric="15"/>
            <column name="Title" value="room2"/>
            <column name="MaxMembers" valueNumeric="10"/>
        </insert>
        <insert tableName="Room">
            <column name="idRooms" valueNumeric="16"/>
            <column name="Title" value="room3"/>
            <column name="MaxMembers" valueNumeric="10"/>
        </insert>
        <insert tableName="Room">
            <column name="idRooms" valueNumeric="17"/>
            <column name="Title" value="room4"/>
            <column name="MaxMembers" valueNumeric="10"/>
        </insert>
        <insert tableName="Room">
            <column name="idRooms" valueNumeric="18"/>
            <column name="Title" value="room5"/>
            <column name="MaxMembers" valueNumeric="10"/>
        </insert>
        <insert tableName="Room">
            <column name="idRooms" valueNumeric="19"/>
            <column name="Title" value="room6"/>
            <column name="MaxMembers" valueNumeric="10"/>
        </insert>
    </changeSet>
    <changeSet author="akarnov (generated)" id="1492450531672-3">
        <insert tableName="User">
            <column name="idUsers" valueNumeric="13"/>
            <column name="Name" value="name1"/>
            <column name="SecondName" value="secondName1"/>
            <column name="Email" value="email1"/>
            <column name="Password" value="password1"/>
        </insert>
        <insert tableName="User">
            <column name="idUsers" valueNumeric="14"/>
            <column name="Name" value="name2"/>
            <column name="SecondName" value="secondName2"/>
            <column name="Email" value="email2"/>
            <column name="Password" value="password2"/>
        </insert>
        <insert tableName="User">
            <column name="idUsers" valueNumeric="15"/>
            <column name="Name" value="name3"/>
            <column name="SecondName" value="secondName3"/>
            <column name="Email" value="email3"/>
            <column name="Password" value="password3"/>
        </insert>
        <insert tableName="User">
            <column name="idUsers" valueNumeric="16"/>
            <column name="Name" value="name4"/>
            <column name="SecondName" value="secondName4"/>
            <column name="Email" value="email4"/>
            <column name="Password" value="password4"/>
        </insert>
        <insert tableName="User">
            <column name="idUsers" valueNumeric="17"/>
            <column name="Name" value="name5"/>
            <column name="SecondName" value="secondName5"/>
            <column name="Email" value="email5"/>
            <column name="Password" value="password5"/>
        </insert>
        <insert tableName="User">
            <column name="idUsers" valueNumeric="18"/>
            <column name="Name" value="name6"/>
            <column name="SecondName" value="secondName6"/>
            <column name="Email" value="email6"/>
            <column name="Password" value="password6"/>
        </insert>
    </changeSet>
    <changeSet author="akarnov (generated)" id="1492450531672-4">
        <insert tableName="User_has_Grup">
            <column name="User_idUsers" valueNumeric="13"/>
            <column name="Grup_idGroups" valueNumeric="10"/>
        </insert>
        <insert tableName="User_has_Grup">
            <column name="User_idUsers" valueNumeric="15"/>
            <column name="Grup_idGroups" valueNumeric="10"/>
        </insert>
        <insert tableName="User_has_Grup">
            <column name="User_idUsers" valueNumeric="13"/>
            <column name="Grup_idGroups" valueNumeric="12"/>
        </insert>
    </changeSet>
</databaseChangeLog>
